ebaysdk/__init__.py
ebaysdk/config.py
ebaysdk/connection.py
ebaysdk/exception.py
ebaysdk/parallel.py
ebaysdk/response.py
ebaysdk/utils.py
ebaysdk/finding/__init__.py
ebaysdk/http/__init__.py
ebaysdk/inventorymanagement/__init__.py
ebaysdk/merchandising/__init__.py
ebaysdk/policies/__init__.py
ebaysdk/poller/__init__.py
ebaysdk/poller/orders.py
ebaysdk/shopping/__init__.py
ebaysdk/soa/__init__.py
ebaysdk/soa/finditem.py
ebaysdk/trading/__init__.py
samples/__init__.py
samples/calls_with_unicode.py
samples/common.py
samples/finding.py
samples/finditem.py
samples/merchandising.py
samples/parallel.py
samples/parallel_gevent.py
samples/policies.py
samples/poller.py
samples/request_dictionary.py
samples/shopping.py
samples/storeMeta.py
samples/t_http.py
samples/test_perf.py
samples/trading.py
tests/__init__.py
tests/test_base.py
tests/test_errors.py
tests/test_request.py
hamin_ebaysdk-2.1.6.dist-info/LICENSE
hamin_ebaysdk-2.1.6.dist-info/METADATA
hamin_ebaysdk-2.1.6.dist-info/WHEEL
hamin_ebaysdk-2.1.6.dist-info/top_level.txt
hamin_ebaysdk-2.1.6.dist-info/RECORD
