Metadata-Version: 2.1
Name: hamin-ebaysdk
Version: 2.1.6
Summary: eBay SDK for Python
Home-page: https://github.com/timotheus/ebaysdk-python
Author: Tim Keefer
Author-email: tkeefer@gmail.com
License: COMMON DEVELOPMENT AND DISTRIBUTION LICENSE (CDDL) Version 1.0
Platform: UNKNOWN
Classifier: Topic :: Internet :: WWW/HTTP
Classifier: Intended Audience :: Developers
Classifier: Programming Language :: Python
Classifier: Programming Language :: Python :: 2
Classifier: Programming Language :: Python :: 2.6
Classifier: Programming Language :: Python :: 2.7
Classifier: Programming Language :: Python :: 3
Classifier: Programming Language :: Python :: 3.5
Provides: ebaysdk
Requires-Dist: lxml
Requires-Dist: requests
